Workbook

Sheet All Findings
A1: Finding (CVE) | B1: Package | C1: Agent | D1: Asset Criticality | E1: CVSS Score | F1: In CISA KEV? | G1: Priority Tier | H1: Description
A2: CVE-2026-33824 | B2: Microsoft Windows 11 Pro 10.0.26200.8037 | C2: Hayzed-Windows-VM | D2: High (domain-facing endpoint) | E2: 9.0-10.0 (Critical) | F2: Yes | G2: =IF(E2="Not yet scored","Pending evaluation",IF(F2="Yes",IF(OR(E2="9.0-10.0 (Critical)",E2="7.0-8.9 (High)"),"P1 - Immediate","P2 - This week (elevated: in KEV)"),IF(OR(E2="9.0-10.0 (Critical)",E2="7.0-8.9 (High)"),"P2 - This week","P3 - Backlog"))) -> P1 - Immediate | H2: Double free in Windows IKE Extension allows an unauthorized attacker to execute code over a network.
A3: CVE-2026-32202 | B3: Microsoft Windows 11 Pro 10.0.26200.8037 | C3: Hayzed-Windows-VM | D3: High (domain-facing endpoint) | E3: 4.0-6.9 (Medium) | F3: Yes | G3: =IF(E3="Not yet scored","Pending evaluation",IF(F3="Yes",IF(OR(E3="9.0-10.0 (Critical)",E3="7.0-8.9 (High)"),"P1 - Immediate","P2 - This week (elevated: in KEV)"),IF(OR(E3="9.0-10.0 (Critical)",E3="7.0-8.9 (High)"),"P2 - This week","P3 - Backlog"))) -> P2 - This week (elevated: in KEV) | H3: Protection mechanism failure in Windows Shell allows an unauthorized attacker to perform spoofing over a network.
A4: CVE-2026-41096 | B4: Microsoft Windows 11 Pro 10.0.26200.8037 | C4: Hayzed-Windows-VM | D4: High (domain-facing endpoint) | E4: 9.0-10.0 (Critical) | F4: No | G4: =IF(E4="Not yet scored","Pending evaluation",IF(F4="Yes",IF(OR(E4="9.0-10.0 (Critical)",E4="7.0-8.9 (High)"),"P1 - Immediate","P2 - This week (elevated: in KEV)"),IF(OR(E4="9.0-10.0 (Critical)",E4="7.0-8.9 (High)"),"P2 - This week","P3 - Backlog"))) -> P2 - This week | H4: Heap-based buffer overflow in Microsoft Windows DNS allows an unauthorized attacker to execute code over a network.
A5: CVE-2026-42904 | B5: Microsoft Windows 11 Pro 10.0.26200.8037 | C5: Hayzed-Windows-VM | D5: High (domain-facing endpoint) | E5: 9.0-10.0 (Critical) | F5: No | G5: =IF(E5="Not yet scored","Pending evaluation",IF(F5="Yes",IF(OR(E5="9.0-10.0 (Critical)",E5="7.0-8.9 (High)"),"P1 - Immediate","P2 - This week (elevated: in KEV)"),IF(OR(E5="9.0-10.0 (Critical)",E5="7.0-8.9 (High)"),"P2 - This week","P3 - Backlog"))) -> P2 - This week | H5: Heap-based buffer overflow in Windows TCP/IP allows an unauthorized attacker to elevate privileges over an adjacent network.
A6: CVE-2026-44815 | B6: Microsoft Windows 11 Pro 10.0.26200.8037 | C6: Hayzed-Windows-VM | D6: High (domain-facing endpoint) | E6: 9.0-10.0 (Critical) | F6: No | G6: =IF(E6="Not yet scored","Pending evaluation",IF(F6="Yes",IF(OR(E6="9.0-10.0 (Critical)",E6="7.0-8.9 (High)"),"P1 - Immediate","P2 - This week (elevated: in KEV)"),IF(OR(E6="9.0-10.0 (Critical)",E6="7.0-8.9 (High)"),"P2 - This week","P3 - Backlog"))) -> P2 - This week | H6: Stack-based buffer overflow in Windows DHCP Client allows an unauthorized attacker to execute code over a network.
A7: CVE-2026-45602 | B7: Microsoft Windows 11 Pro 10.0.26200.8037 | C7: Hayzed-Windows-VM | D7: High (domain-facing endpoint) | E7: 9.0-10.0 (Critical) | F7: No | G7: =IF(E7="Not yet scored","Pending evaluation",IF(F7="Yes",IF(OR(E7="9.0-10.0 (Critical)",E7="7.0-8.9 (High)"),"P1 - Immediate","P2 - This week (elevated: in KEV)"),IF(OR(E7="9.0-10.0 (Critical)",E7="7.0-8.9 (High)"),"P2 - This week","P3 - Backlog"))) -> P2 - This week | H7: No cwe for this issue in Windows DHCP Server allows an unauthorized attacker to perform tampering over a network.
A8: CVE-2026-45657 | B8: Microsoft Windows 11 Pro 10.0.26200.8037 | C8: Hayzed-Windows-VM | D8: High (domain-facing endpoint) | E8: 9.0-10.0 (Critical) | F8: No | G8: =IF(E8="Not yet scored","Pending evaluation",IF(F8="Yes",IF(OR(E8="9.0-10.0 (Critical)",E8="7.0-8.9 (High)"),"P1 - Immediate","P2 - This week (elevated: in KEV)"),IF(OR(E8="9.0-10.0 (Critical)",E8="7.0-8.9 (High)"),"P2 - This week","P3 - Backlog"))) -> P2 - This week | H8: Use after free in Windows Kernel allows an unauthorized attacker to execute code over a network.
A9: CVE-2026-47291 | B9: Microsoft Windows 11 Pro 10.0.26200.8037 | C9: Hayzed-Windows-VM | D9: High (domain-facing endpoint) | E9: 9.0-10.0 (Critical) | F9: No | G9: =IF(E9="Not yet scored","Pending evaluation",IF(F9="Yes",IF(OR(E9="9.0-10.0 (Critical)",E9="7.0-8.9 (High)"),"P1 - Immediate","P2 - This week (elevated: in KEV)"),IF(OR(E9="9.0-10.0 (Critical)",E9="7.0-8.9 (High)"),"P2 - This week","P3 - Backlog"))) -> P2 - This week | H9: Integer overflow or wraparound in Windows HTTP.sys allows an unauthorized attacker to execute code over a network.
A10: CVE-2026-10536 | B10: libcurl4t64 | C10: hayzed | D10: Medium (Linux internal server) | E10: 9.0-10.0 (Critical) | F10: No | G10: =IF(E10="Not yet scored","Pending evaluation",IF(F10="Yes",IF(OR(E10="9.0-10.0 (Critical)",E10="7.0-8.9 (High)"),"P1 - Immediate","P2 - This week (elevated: in KEV)"),IF(OR(E10="9.0-10.0 (Critical)",E10="7.0-8.9 (High)"),"P2 - This week","P3 - Backlog"))) -> P2 - This week | H10: A use-after-free vulnerability exists in libcurl when an applicationconfigures an HTTP/2 stream-dependency tree via `CURLOPT_STREAM_DEPENDS` or`CURLOPT_STREAM_DEPENDS_E`, subsequently invokes `curl_easy_reset()`, andfinally terminates the handle with `curl_easy_cleanup()`. During this finalcleanup phase, libcurl attempts to access and modify an internal structurethat was already deallocated during the reset operation.
A11: CVE-2026-10536 | B11: curl | C11: hayzed | D11: Medium (Linux internal server) | E11: 9.0-10.0 (Critical) | F11: No | G11: =IF(E11="Not yet scored","Pending evaluation",IF(F11="Yes",IF(OR(E11="9.0-10.0 (Critical)",E11="7.0-8.9 (High)"),"P1 - Immediate","P2 - This week (elevated: in KEV)"),IF(OR(E11="9.0-10.0 (Critical)",E11="7.0-8.9 (High)"),"P2 - This week","P3 - Backlog"))) -> P2 - This week | H11: A use-after-free vulnerability exists in libcurl when an applicationconfigures an HTTP/2 stream-dependency tree via `CURLOPT_STREAM_DEPENDS` or`CURLOPT_STREAM_DEPENDS_E`, subsequently invokes `curl_easy_reset()`, andfinally terminates the handle with `curl_easy_cleanup()`. During this finalcleanup phase, libcurl attempts to access and modify an internal structurethat was already deallocated during the reset operation.
A12: CVE-2026-10536 | B12: libcurl3t64-gnutls | C12: hayzed | D12: Medium (Linux internal server) | E12: 9.0-10.0 (Critical) | F12: No | G12: =IF(E12="Not yet scored","Pending evaluation",IF(F12="Yes",IF(OR(E12="9.0-10.0 (Critical)",E12="7.0-8.9 (High)"),"P1 - Immediate","P2 - This week (elevated: in KEV)"),IF(OR(E12="9.0-10.0 (Critical)",E12="7.0-8.9 (High)"),"P2 - This week","P3 - Backlog"))) -> P2 - This week | H12: A use-after-free vulnerability exists in libcurl when an applicationconfigures an HTTP/2 stream-dependency tree via `CURLOPT_STREAM_DEPENDS` or`CURLOPT_STREAM_DEPENDS_E`, subsequently invokes `curl_easy_reset()`, andfinally terminates the handle with `curl_easy_cleanup()`. During this finalcleanup phase, libcurl attempts to access and modify an internal structurethat was already deallocated during the reset operation.
A13: CVE-2026-11564 | B13: libcurl4t64 | C13: hayzed | D13: Medium (Linux internal server) | E13: 9.0-10.0 (Critical) | F13: No | G13: =IF(E13="Not yet scored","Pending evaluation",IF(F13="Yes",IF(OR(E13="9.0-10.0 (Critical)",E13="7.0-8.9 (High)"),"P1 - Immediate","P2 - This week (elevated: in KEV)"),IF(OR(E13="9.0-10.0 (Critical)",E13="7.0-8.9 (High)"),"P2 - This week","P3 - Backlog"))) -> P2 - This week | H13: libcurl keeps previously used connections in a connection pool for subsequenttransfers to reuse if one of them matches the setup.An easy handle that first uses default native CA trust can continue trustingthe native platform store after the application switches that same handle tocustom CA material for a later transfer.
... A959: CVE-2026-53137 | B959: linux-image-7.0.0-29-generic | C959: hayzed | D959: Medium (Linux internal server) | E959: Not yet scored | F959: No | G959: =IF(E959="Not yet scored","Pending evaluation",IF(F959="Yes",IF(OR(E959="9.0-10.0 (Critical)",E959="7.0-8.9 (High)"),"P1 - Immediate","P2 - This week (elevated: in KEV)"),IF(OR(E959="9.0-10.0 (Critical)",E959="7.0-8.9 (High)"),"P2 - This week","P3 - Backlog"))) -> Pending evaluation | H959: In the Linux kernel, the following vulnerability has been resolved:drm/amd/display: Clamp HDMI HDCP2 rx_id_list read to buffer size[Why & How]During HDCP 2.x repeater authentication over HDMI, the driver reads thesink's RxStatus register and extracts a 10-bit message size field (maxvalue 1023). This value is used as the read length for the ReceiverIDlist without being clamped to the size of the destination bufferrx_id_list[177]. A malicious HDMI repeater could advertise a messagesize larger than the buffer, causing an out-of-bounds write during theI2C read.Clamp the read length in mod_hdcp_read_rx_id_list() to the size of therx_id_list buffer, matching the approach already used in the DP branch.(cherry picked from commit 229212219e4247d9486f8ba41ef087358490be09)
A960: CVE-2026-53138 | B960: linux-image-7.0.0-29-generic | C960: hayzed | D960: Medium (Linux internal server) | E960: Not yet scored | F960: No | G960: =IF(E960="Not yet scored","Pending evaluation",IF(F960="Yes",IF(OR(E960="9.0-10.0 (Critical)",E960="7.0-8.9 (High)"),"P1 - Immediate","P2 - This week (elevated: in KEV)"),IF(OR(E960="9.0-10.0 (Critical)",E960="7.0-8.9 (High)"),"P2 - This week","P3 - Backlog"))) -> Pending evaluation
A961: CVE-2026-53139 | B961: linux-image-7.0.0-29-generic | C961: hayzed | D961: Medium (Linux internal server) | E961: Not yet scored | F961: No | G961: =IF(E961="Not yet scored","Pending evaluation",IF(F961="Yes",IF(OR(E961="9.0-10.0 (Critical)",E961="7.0-8.9 (High)"),"P1 - Immediate","P2 - This week (elevated: in KEV)"),IF(OR(E961="9.0-10.0 (Critical)",E961="7.0-8.9 (High)"),"P2 - This week","P3 - Backlog"))) -> Pending evaluation | H961: In the Linux kernel, the following vulnerability has been resolved:drm/v3d: Skip CSD when it has zeroed workgroupsA compute shader dispatch encodes its workgroup counts in the CFG0..CFG2registers. Kicking off a dispatch with a zero count in any of the threedimensions is invalid. First, the hardware will process 0 as 65536,while the user-space driver exposes a maximum of 65535. Over that, asubmission with a zeroed workgroup dimension should be a no-op.These zeroed counts can reach the dispatch path through an indirect CSDjob, whose workgroup counts are only known once the indirect buffer isread and may legitimately be zero, but such scenario should only result ina no-op.Overwrite the indirect CSD job workgroup counts with the indirect BOones, even if they are zeroed, and don't submit the job to the hardwarewhen any of the workgroup counts is zero, so the job completes immediatelyinstead of running the shader.
A962: CVE-2026-53140 | B962: linux-image-7.0.0-29-generic | C962: hayzed | D962: Medium (Linux internal server) | E962: Not yet scored | F962: No | G962: =IF(E962="Not yet scored","Pending evaluation",IF(F962="Yes",IF(OR(E962="9.0-10.0 (Critical)",E962="7.0-8.9 (High)"),"P1 - Immediate","P2 - This week (elevated: in KEV)"),IF(OR(E962="9.0-10.0 (Critical)",E962="7.0-8.9 (High)"),"P2 - This week","P3 - Backlog"))) -> Pending evaluation | H962: In the Linux kernel, the following vulnerability has been resolved:drm/v3d: Fix vaddr leak when indirect CSD has zeroed workgroupsv3d_rewrite_csd_job_wg_counts_from_indirect() maps both the indirectbuffer and the workgroup buffer and is expected to release them beforereturning. When any of the workgroup counts read from the buffer is zero,the function bailed out early and skipped the cleanup, leaking the vaddrmappings of both BOs.Jump to the cleanup path instead of returning directly, so the mappingsare always dropped.
A963: CVE-2026-53141 | B963: linux-image-7.0.0-29-generic | C963: hayzed | D963: Medium (Linux internal server) | E963: Not yet scored | F963: No | G963: =IF(E963="Not yet scored","Pending evaluation",IF(F963="Yes",IF(OR(E963="9.0-10.0 (Critical)",E963="7.0-8.9 (High)"),"P1 - Immediate","P2 - This week (elevated: in KEV)"),IF(OR(E963="9.0-10.0 (Critical)",E963="7.0-8.9 (High)"),"P2 - This week","P3 - Backlog"))) -> Pending evaluation | H963: In the Linux kernel, the following vulnerability has been resolved:drm/v3d: Fix global performance monitor reference countingIn the SET_GLOBAL ioctl, v3d_perfmon_find() bumps the reference count onthe perfmon it returns, but v3d_perfmon_set_global_ioctl() andv3d_perfmon_delete() fail to release that reference on several paths: 1. v3d_perfmon_set_global_ioctl() leaks the reference on its error paths. 2. CLEAR_GLOBAL leaks both the find reference and the reference previously stashed in v3d->global_perfmon by the SET_GLOBAL ioctl that configured it. 3. Destroying a perfmon that is the current global perfmon leaks the reference stashed by the SET_GLOBAL ioctl.Release each of these references explicitly.
A964: CVE-2026-53142 | B964: linux-image-7.0.0-29-generic | C964: hayzed | D964: Medium (Linux internal server) | E964: Not yet scored | F964: No | G964: =IF(E964="Not yet scored","Pending evaluation",IF(F964="Yes",IF(OR(E964="9.0-10.0 (Critical)",E964="7.0-8.9 (High)"),"P1 - Immediate","P2 - This week (elevated: in KEV)"),IF(OR(E964="9.0-10.0 (Critical)",E964="7.0-8.9 (High)"),"P2 - This week","P3 - Backlog"))) -> Pending evaluation | H964: In the Linux kernel, the following vulnerability has been resolved:drm/xe/display: fix oops in suspend/shutdown without displayThe xe driver keeps track of whether to probe display, and whetherdisplay hardware is there, using xe->info.probe_display. It gets set tofalse if there's no display after intel_display_device_probe(). However,the display may also be disabled via fuses, detected at a later time inintel_display_device_info_runtime_init().In this case, the xe driver does for_each_intel_crtc() on uninitializedmode config in xe_display_flush_cleanup_work(), leading to a NULLpointer dereference, and generally calls display code with display infocleared.Check for intel_display_device_present() afterintel_display_device_info_runtime_init(), and resetxe->info.probe_display as necessary. Also do unset_display_features()for completeness, although display runtime init has already donethat. This will need to be unified across all cases later.Move intel_display_device_info_runtime_init() call slightly earlier,similar to i915, to avoid a bunch of unnecessary setup for no displaycases.Note #1: The xe driver has no business doing low level display plumbinglike for_each_intel_crtc() to begin with. It all needs to happen indisplay code.Note #2: The actual bug is present already in commit 44e694958b95("drm/xe/display: Implement display support"), but the oops was likelyintroduced later at commit ddf6492e0e50 ("drm/xe/display: Make displaysuspend/resume work on discrete").(cherry picked from commit 7c3eb9f47533220888a67266448185fd0775d4da)
A965: CVE-2026-53143 | B965: linux-image-7.0.0-29-generic | C965: hayzed | D965: Medium (Linux internal server) | E965: Not yet scored | F965: No | G965: =IF(E965="Not yet scored","Pending evaluation",IF(F965="Yes",IF(OR(E965="9.0-10.0 (Critical)",E965="7.0-8.9 (High)"),"P1 - Immediate","P2 - This week (elevated: in KEV)"),IF(OR(E965="9.0-10.0 (Critical)",E965="7.0-8.9 (High)"),"P2 - This week","P3 - Backlog"))) -> Pending evaluation
A966: CVE-2026-53144 | B966: linux-image-7.0.0-29-generic | C966: hayzed | D966: Medium (Linux internal server) | E966: Not yet scored | F966: No | G966: =IF(E966="Not yet scored","Pending evaluation",IF(F966="Yes",IF(OR(E966="9.0-10.0 (Critical)",E966="7.0-8.9 (High)"),"P1 - Immediate","P2 - This week (elevated: in KEV)"),IF(OR(E966="9.0-10.0 (Critical)",E966="7.0-8.9 (High)"),"P2 - This week","P3 - Backlog"))) -> Pending evaluation | H966: In the Linux kernel, the following vulnerability has been resolved:drm/amdkfd: fix NULL dereference in get_queue_ids()When usr_queue_id_array is NULL and num_queues is non-zero,get_queue_ids() returns NULL. The callers check only IS_ERR() on thereturn value; since IS_ERR(NULL) == false the check passes, andsuspend_queues() calls q_array_invalidate() which immediatelydereferences NULL while iterating num_queues times.Userspace can trigger this via kfd_ioctl_set_debug_trap() by supplyingnum_queues > 0 with a zero queue_array_ptr, causing a kernel panic.A NULL usr_queue_id_array with num_queues == 0 is a legitimate no-op(q_array_invalidate never executes, and resume_queues already guardsall queue_ids dereferences behind a NULL check). Return ERR_PTR(-EINVAL)only when num_queues is non-zero and the pointer is absent; both callersalready propagate IS_ERR() returns correctly to userspace.(cherry picked from commit f165a82cdf503884bb1797771c61b2fcc72113d4)
A967: CVE-2026-53145 | B967: linux-image-7.0.0-29-generic | C967: hayzed | D967: Medium (Linux internal server) | E967: Not yet scored | F967: No | G967: =IF(E967="Not yet scored","Pending evaluation",IF(F967="Yes",IF(OR(E967="9.0-10.0 (Critical)",E967="7.0-8.9 (High)"),"P1 - Immediate","P2 - This week (elevated: in KEV)"),IF(OR(E967="9.0-10.0 (Critical)",E967="7.0-8.9 (High)"),"P2 - This week","P3 - Backlog"))) -> Pending evaluation
A968: CVE-2026-53146 | B968: linux-image-7.0.0-29-generic | C968: hayzed | D968: Medium (Linux internal server) | E968: Not yet scored | F968: No | G968: =IF(E968="Not yet scored","Pending evaluation",IF(F968="Yes",IF(OR(E968="9.0-10.0 (Critical)",E968="7.0-8.9 (High)"),"P1 - Immediate","P2 - This week (elevated: in KEV)"),IF(OR(E968="9.0-10.0 (Critical)",E968="7.0-8.9 (High)"),"P2 - This week","P3 - Backlog"))) -> Pending evaluation | H968: In the Linux kernel, the following vulnerability has been resolved:thunderbolt: Limit XDomain response copy to actual frame sizetb_xdomain_copy() copies req->response_size bytes from the receivedpacket buffer regardless of the actual frame size. When a shortresponse arrives, this reads past the valid frame data in the DMApool buffer into stale contents from previous transactions.Use the minimum of frame size and expected response size for thecopy length.
A969: CVE-2026-53147 | B969: linux-image-7.0.0-29-generic | C969: hayzed | D969: Medium (Linux internal server) | E969: Not yet scored | F969: No | G969: =IF(E969="Not yet scored","Pending evaluation",IF(F969="Yes",IF(OR(E969="9.0-10.0 (Critical)",E969="7.0-8.9 (High)"),"P1 - Immediate","P2 - This week (elevated: in KEV)"),IF(OR(E969="9.0-10.0 (Critical)",E969="7.0-8.9 (High)"),"P2 - This week","P3 - Backlog"))) -> Pending evaluation | H969: In the Linux kernel, the following vulnerability has been resolved:thunderbolt: Validate XDomain request packet size before type casttb_xdp_handle_request() casts the received packet buffer toprotocol-specific structs without verifying that the allocationis large enough for the target type. A peer can send a minimalXDomain packet that passes the generic header length check but isshorter than the struct accessed after the cast, causing out-of-bounds reads from the kmemdup allocation.Plumb the packet length through xdomain_request_work and validateit against the expected struct size before each cast.
A970: CVE-2026-53148 | B970: linux-image-7.0.0-29-generic | C970: hayzed | D970: Medium (Linux internal server) | E970: Not yet scored | F970: No | G970: =IF(E970="Not yet scored","Pending evaluation",IF(F970="Yes",IF(OR(E970="9.0-10.0 (Critical)",E970="7.0-8.9 (High)"),"P1 - Immediate","P2 - This week (elevated: in KEV)"),IF(OR(E970="9.0-10.0 (Critical)",E970="7.0-8.9 (High)"),"P2 - This week","P3 - Backlog"))) -> Pending evaluation
A971: CVE-2026-53149 | B971: linux-image-7.0.0-29-generic | C971: hayzed | D971: Medium (Linux internal server) | E971: Not yet scored | F971: No | G971: =IF(E971="Not yet scored","Pending evaluation",IF(F971="Yes",IF(OR(E971="9.0-10.0 (Critical)",E971="7.0-8.9 (High)"),"P1 - Immediate","P2 - This week (elevated: in KEV)"),IF(OR(E971="9.0-10.0 (Critical)",E971="7.0-8.9 (High)"),"P2 - This week","P3 - Backlog"))) -> Pending evaluation | H971: In the Linux kernel, the following vulnerability has been resolved:thunderbolt: Bound root directory content to block size__tb_property_parse_dir() does not check that content_offset +content_len fits within block_len for the root directory case.When rootdir->length equals or exceeds block_len - 2, the entryloop reads past the allocated property block.Add a bounds check after computing content_offset and content_lento reject directories whose content extends past the block.
A972: CVE-2026-53150 | B972: linux-image-7.0.0-29-generic | C972: hayzed | D972: Medium (Linux internal server) | E972: Not yet scored | F972: No | G972: =IF(E972="Not yet scored","Pending evaluation",IF(F972="Yes",IF(OR(E972="9.0-10.0 (Critical)",E972="7.0-8.9 (High)"),"P1 - Immediate","P2 - This week (elevated: in KEV)"),IF(OR(E972="9.0-10.0 (Critical)",E972="7.0-8.9 (High)"),"P2 - This week","P3 - Backlog"))) -> Pending evaluation | H972: In the Linux kernel, the following vulnerability has been resolved:thunderbolt: Reject zero-length property entries in validatortb_property_entry_valid() accepts entries with length == 0 forDIRECTORY, DATA, and TEXT types. A zero-length TEXT entry passesvalidation but causes an underflow in the null-termination logic: property->value.text[property->length * 4 - 1] = '\0';When property->length is 0 this writes to offset -1 relative tothe allocation.Reject zero-length entries early in the validator since they have novalid representation in the XDomain property protocol.
A973: CVE-2026-53151 | B973: linux-image-7.0.0-29-generic | C973: hayzed | D973: Medium (Linux internal server) | E973: Not yet scored | F973: No | G973: =IF(E973="Not yet scored","Pending evaluation",IF(F973="Yes",IF(OR(E973="9.0-10.0 (Critical)",E973="7.0-8.9 (High)"),"P1 - Immediate","P2 - This week (elevated: in KEV)"),IF(OR(E973="9.0-10.0 (Critical)",E973="7.0-8.9 (High)"),"P2 - This week","P3 - Backlog"))) -> Pending evaluation | H973: In the Linux kernel, the following vulnerability has been resolved:rxrpc: Fix the ACK parser to extract the SACK table for parsingFix modification of the received skbuff in rxrpc_input_soft_acks() and apotential incorrect access of the buffer in a fragmented UDP packet (thepacket would probably have to be deliberately pre-generated as fragmented)when AF_RXRPC tries to extract the contents of the SACK table by copyingout the contents of the SACK table into a buffer before attempting to parseAF_RXRPC assumes that it can just call skb_condense() and then validlyaccess the SACK table from skb->data and that it will be a flat buffer -but skb_condense() can silently fail to do anything under somecircumstances.Note that whilst rxrpc_input_soft_acks() should be able to parse extendedACKs, the rest of AF_RXRPC doesn't currently support that.Further, there's then no need to call skb_condense() in rxrpc_input_ack(),so don't.
A974: CVE-2026-53152 | B974: linux-image-7.0.0-29-generic | C974: hayzed | D974: Medium (Linux internal server) | E974: Not yet scored | F974: No | G974: =IF(E974="Not yet scored","Pending evaluation",IF(F974="Yes",IF(OR(E974="9.0-10.0 (Critical)",E974="7.0-8.9 (High)"),"P1 - Immediate","P2 - This week (elevated: in KEV)"),IF(OR(E974="9.0-10.0 (Critical)",E974="7.0-8.9 (High)"),"P2 - This week","P3 - Backlog"))) -> Pending evaluation
A975: CVE-2026-53153 | B975: linux-image-7.0.0-29-generic | C975: hayzed | D975: Medium (Linux internal server) | E975: Not yet scored | F975: No | G975: =IF(E975="Not yet scored","Pending evaluation",IF(F975="Yes",IF(OR(E975="9.0-10.0 (Critical)",E975="7.0-8.9 (High)"),"P1 - Immediate","P2 - This week (elevated: in KEV)"),IF(OR(E975="9.0-10.0 (Critical)",E975="7.0-8.9 (High)"),"P2 - This week","P3 - Backlog"))) -> Pending evaluation
A976: CVE-2026-53154 | B976: linux-image-7.0.0-29-generic | C976: hayzed | D976: Medium (Linux internal server) | E976: Not yet scored | F976: No | G976: =IF(E976="Not yet scored","Pending evaluation",IF(F976="Yes",IF(OR(E976="9.0-10.0 (Critical)",E976="7.0-8.9 (High)"),"P1 - Immediate","P2 - This week (elevated: in KEV)"),IF(OR(E976="9.0-10.0 (Critical)",E976="7.0-8.9 (High)"),"P2 - This week","P3 - Backlog"))) -> Pending evaluation
A977: CVE-2026-53155 | B977: linux-image-7.0.0-29-generic | C977: hayzed | D977: Medium (Linux internal server) | E977: Not yet scored | F977: No | G977: =IF(E977="Not yet scored","Pending evaluation",IF(F977="Yes",IF(OR(E977="9.0-10.0 (Critical)",E977="7.0-8.9 (High)"),"P1 - Immediate","P2 - This week (elevated: in KEV)"),IF(OR(E977="9.0-10.0 (Critical)",E977="7.0-8.9 (High)"),"P2 - This week","P3 - Backlog"))) -> Pending evaluation
A978: CVE-2026-53156 | B978: linux-image-7.0.0-29-generic | C978: hayzed | D978: Medium (Linux internal server) | E978: Not yet scored | F978: No | G978: =IF(E978="Not yet scored","Pending evaluation",IF(F978="Yes",IF(OR(E978="9.0-10.0 (Critical)",E978="7.0-8.9 (High)"),"P1 - Immediate","P2 - This week (elevated: in KEV)"),IF(OR(E978="9.0-10.0 (Critical)",E978="7.0-8.9 (High)"),"P2 - This week","P3 - Backlog"))) -> Pending evaluation
A979: CVE-2026-53157 | B979: linux-image-7.0.0-29-generic | C979: hayzed | D979: Medium (Linux internal server) | E979: Not yet scored | F979: No | G979: =IF(E979="Not yet scored","Pending evaluation",IF(F979="Yes",IF(OR(E979="9.0-10.0 (Critical)",E979="7.0-8.9 (High)"),"P1 - Immediate","P2 - This week (elevated: in KEV)"),IF(OR(E979="9.0-10.0 (Critical)",E979="7.0-8.9 (High)"),"P2 - This week","P3 - Backlog"))) -> Pending evaluation
A980: CVE-2026-53158 | B980: linux-image-7.0.0-29-generic | C980: hayzed | D980: Medium (Linux internal server) | E980: Not yet scored | F980: No | G980: =IF(E980="Not yet scored","Pending evaluation",IF(F980="Yes",IF(OR(E980="9.0-10.0 (Critical)",E980="7.0-8.9 (High)"),"P1 - Immediate","P2 - This week (elevated: in KEV)"),IF(OR(E980="9.0-10.0 (Critical)",E980="7.0-8.9 (High)"),"P2 - This week","P3 - Backlog"))) -> Pending evaluation
A981: CVE-2026-53159 | B981: linux-image-7.0.0-29-generic | C981: hayzed | D981: Medium (Linux internal server) | E981: Not yet scored | F981: No | G981: =IF(E981="Not yet scored","Pending evaluation",IF(F981="Yes",IF(OR(E981="9.0-10.0 (Critical)",E981="7.0-8.9 (High)"),"P1 - Immediate","P2 - This week (elevated: in KEV)"),IF(OR(E981="9.0-10.0 (Critical)",E981="7.0-8.9 (High)"),"P2 - This week","P3 - Backlog"))) -> Pending evaluation
A982: CVE-2026-53163 | B982: linux-image-7.0.0-29-generic | C982: hayzed | D982: Medium (Linux internal server) | E982: Not yet scored | F982: No | G982: =IF(E982="Not yet scored","Pending evaluation",IF(F982="Yes",IF(OR(E982="9.0-10.0 (Critical)",E982="7.0-8.9 (High)"),"P1 - Immediate","P2 - This week (elevated: in KEV)"),IF(OR(E982="9.0-10.0 (Critical)",E982="7.0-8.9 (High)"),"P2 - This week","P3 - Backlog"))) -> Pending evaluation
A983: CVE-2026-53164 | B983: linux-image-7.0.0-29-generic | C983: hayzed | D983: Medium (Linux internal server) | E983: Not yet scored | F983: No | G983: =IF(E983="Not yet scored","Pending evaluation",IF(F983="Yes",IF(OR(E983="9.0-10.0 (Critical)",E983="7.0-8.9 (High)"),"P1 - Immediate","P2 - This week (elevated: in KEV)"),IF(OR(E983="9.0-10.0 (Critical)",E983="7.0-8.9 (High)"),"P2 - This week","P3 - Backlog"))) -> Pending evaluation
A984: CVE-2026-53165 | B984: linux-image-7.0.0-29-generic | C984: hayzed | D984: Medium (Linux internal server) | E984: Not yet scored | F984: No | G984: =IF(E984="Not yet scored","Pending evaluation",IF(F984="Yes",IF(OR(E984="9.0-10.0 (Critical)",E984="7.0-8.9 (High)"),"P1 - Immediate","P2 - This week (elevated: in KEV)"),IF(OR(E984="9.0-10.0 (Critical)",E984="7.0-8.9 (High)"),"P2 - This week","P3 - Backlog"))) -> Pending evaluation
A985: CVE-2026-53166 | B985: linux-image-7.0.0-29-generic | C985: hayzed | D985: Medium (Linux internal server) | E985: Not yet scored | F985: No | G985: =IF(E985="Not yet scored","Pending evaluation",IF(F985="Yes",IF(OR(E985="9.0-10.0 (Critical)",E985="7.0-8.9 (High)"),"P1 - Immediate","P2 - This week (elevated: in KEV)"),IF(OR(E985="9.0-10.0 (Critical)",E985="7.0-8.9 (High)"),"P2 - This week","P3 - Backlog"))) -> Pending evaluation
A986: CVE-2026-53167 | B986: linux-image-7.0.0-29-generic | C986: hayzed | D986: Medium (Linux internal server) | E986: Not yet scored | F986: No | G986: =IF(E986="Not yet scored","Pending evaluation",IF(F986="Yes",IF(OR(E986="9.0-10.0 (Critical)",E986="7.0-8.9 (High)"),"P1 - Immediate","P2 - This week (elevated: in KEV)"),IF(OR(E986="9.0-10.0 (Critical)",E986="7.0-8.9 (High)"),"P2 - This week","P3 - Backlog"))) -> Pending evaluation | H986: In the Linux kernel, the following vulnerability has been resolved:fuse: limit FUSE_NOTIFY_RETRIEVE to uptodate foliosFUSE_NOTIFY_RETRIEVE must be limited to uptodate folios; !uptodate folioscan contain uninitialized data.Since FUSE_NOTIFY_RETRIEVE is intended to only return data that is alreadyin the page cache and not wait for data from the FUSE daemon, treat!uptodate folios as if they weren't present.This only has security impact on systems that don't enable automaticzero-initialization of all page allocations viaCONFIG_INIT_ON_ALLOC_DEFAULT_ON or init_on_alloc=1.
A987: CVE-2026-53168 | B987: linux-image-7.0.0-29-generic | C987: hayzed | D987: Medium (Linux internal server) | E987: Not yet scored | F987: No | G987: =IF(E987="Not yet scored","Pending evaluation",IF(F987="Yes",IF(OR(E987="9.0-10.0 (Critical)",E987="7.0-8.9 (High)"),"P1 - Immediate","P2 - This week (elevated: in KEV)"),IF(OR(E987="9.0-10.0 (Critical)",E987="7.0-8.9 (High)"),"P2 - This week","P3 - Backlog"))) -> Pending evaluation
A988: CVE-2026-53169 | B988: linux-image-7.0.0-29-generic | C988: hayzed | D988: Medium (Linux internal server) | E988: Not yet scored | F988: No | G988: =IF(E988="Not yet scored","Pending evaluation",IF(F988="Yes",IF(OR(E988="9.0-10.0 (Critical)",E988="7.0-8.9 (High)"),"P1 - Immediate","P2 - This week (elevated: in KEV)"),IF(OR(E988="9.0-10.0 (Critical)",E988="7.0-8.9 (High)"),"P2 - This week","P3 - Backlog"))) -> Pending evaluation | H988: In the Linux kernel, the following vulnerability has been resolved:accel/ethosu: reject NPU_OP_RESIZE commands from userspaceNPU_OP_RESIZE is a U85-only command that the driver does not yetimplement. The existing WARN_ON(1) placeholder fires unconditionallywhenever userspace submits this command via DRM_IOCTL_ETHOSU_GEM_CREATE,causing unbounded kernel log spam.If panic_on_warn is set the kernel panics, giving any unprivileged userwith access to the DRM device a trivial denial-of-service primitive.Replace the WARN_ON(1) with an explicit -EINVAL return so the ioctlrejects the command before it reaches hardware.
A989: CVE-2026-53170 | B989: linux-image-7.0.0-29-generic | C989: hayzed | D989: Medium (Linux internal server) | E989: Not yet scored | F989: No | G989: =IF(E989="Not yet scored","Pending evaluation",IF(F989="Yes",IF(OR(E989="9.0-10.0 (Critical)",E989="7.0-8.9 (High)"),"P1 - Immediate","P2 - This week (elevated: in KEV)"),IF(OR(E989="9.0-10.0 (Critical)",E989="7.0-8.9 (High)"),"P2 - This week","P3 - Backlog"))) -> Pending evaluation | H989: In the Linux kernel, the following vulnerability has been resolved:accel/ethosu: reject DMA commands with uninitialized lengthcmd_state_init() initializes the command state with memset(0xff),leaving dma->len at U64_MAX to signal missing setup. The only setteris NPU_SET_DMA0_LEN; if userspace omits this command and issuesNPU_OP_DMA_START, dma->len remains U64_MAX.In dma_length(), a positive stride added to U64_MAX wraps to a smallvalue. With size0 == 1, check_mul_overflow() does not trigger anddma_length() returns 0 instead of U64_MAX. The caller's U64_MAX checkthen passes, region_size[] stays 0, and the bounds check inethosu_job.c is bypassed, allowing hardware to execute DMA with stalephysical addresses.Fix by checking for U64_MAX at the start of dma_length() before anyarithmetic, consistent with the sentinel value used throughout thedriver to detect uninitialized fields.
A990: CVE-2026-53171 | B990: linux-image-7.0.0-29-generic | C990: hayzed | D990: Medium (Linux internal server) | E990: Not yet scored | F990: No | G990: =IF(E990="Not yet scored","Pending evaluation",IF(F990="Yes",IF(OR(E990="9.0-10.0 (Critical)",E990="7.0-8.9 (High)"),"P1 - Immediate","P2 - This week (elevated: in KEV)"),IF(OR(E990="9.0-10.0 (Critical)",E990="7.0-8.9 (High)"),"P2 - This week","P3 - Backlog"))) -> Pending evaluation | H990: In the Linux kernel, the following vulnerability has been resolved:accel/ethosu: fix arithmetic issues in dma_length()dma_length() derives DMA region usage from command stream values andupdates region_size[]: len = ((len + stride[0]) * size0 + stride[1]) * size1 region_size[region] = max(..., len + dma->offset)Several arithmetic issues can corrupt the derived region size:- signed stride values may underflow when added to len- intermediate multiplications may overflow- len + dma->offset may overflow during region_size updates- dma_length() error returns were not validated by the callerregion_size[] is later used by ethosu_job.c to validate command streamaccesses against GEM buffer sizes. Arithmetic wraparound can thereforeunder-report region usage and bypass the bounds validation.Fix by validating signed additions, using overflow helpers formultiplications and offset updates, and propagating dma_length()failures to the caller.
A991: CVE-2026-53172 | B991: linux-image-7.0.0-29-generic | C991: hayzed | D991: Medium (Linux internal server) | E991: Not yet scored | F991: No | G991: =IF(E991="Not yet scored","Pending evaluation",IF(F991="Yes",IF(OR(E991="9.0-10.0 (Critical)",E991="7.0-8.9 (High)"),"P1 - Immediate","P2 - This week (elevated: in KEV)"),IF(OR(E991="9.0-10.0 (Critical)",E991="7.0-8.9 (High)"),"P2 - This week","P3 - Backlog"))) -> Pending evaluation | H991: In the Linux kernel, the following vulnerability has been resolved:accel/ethosu: fix IFM region index out-of-bounds in command stream parserNPU_SET_IFM_REGION extracts the region index with param & 0x7f, givinga maximum value of 127. However region_size[] and output_region[] instruct ethosu_validated_cmdstream_info are both sized toNPU_BASEP_REGION_MAX (8), giving valid indices [0..7].Every other region assignment in the same switch uses param & 0x7: NPU_SET_OFM_REGION: st.ofm.region = param & 0x7; NPU_SET_IFM2_REGION: st.ifm2.region = param & 0x7; NPU_SET_WEIGHT_REGION: st.weight[0].region = param & 0x7; NPU_SET_SCALE_REGION: st.scale[0].region = param & 0x7;The 0x7f mask on IFM is inconsistent and appears to be a typo.feat_matrix_length() and calc_sizes() use the region index directlyas an array subscript into the kzalloc'd info struct: info->region_size[fm->region] = max(...);A userspace caller supplying NPU_SET_IFM_REGION with param > 7 causesa write up to 127*8 = 1016 bytes past the start of region_size[],corrupting adjacent kernel heap data.Fix by applying the same & 0x7 mask used by all other regionassignments.
A992: CVE-2026-53173 | B992: linux-image-7.0.0-29-generic | C992: hayzed | D992: Medium (Linux internal server) | E992: Not yet scored | F992: No | G992: =IF(E992="Not yet scored","Pending evaluation",IF(F992="Yes",IF(OR(E992="9.0-10.0 (Critical)",E992="7.0-8.9 (High)"),"P1 - Immediate","P2 - This week (elevated: in KEV)"),IF(OR(E992="9.0-10.0 (Critical)",E992="7.0-8.9 (High)"),"P2 - This week","P3 - Backlog"))) -> Pending evaluation | H992: In the Linux kernel, the following vulnerability has been resolved:accel/ethosu: fix OOB write in ethosu_gem_cmdstream_copy_and_validate()The command stream parsing loop increments the index variable a secondtime when a 64-bit command word is encountered (bit 14 set), but doesnot re-check the loop bound before writing the second word: for (i = 0; i < size / 4; i++) { bocmds[i] = cmds[0]; if (cmd & 0x4000) { i++; bocmds[i] = cmds[1]; /* unchecked */ } }The buffer bocmds is backed by a DMA allocation of exactly size bytesfrom drm_gem_dma_create(ddev, size), giving valid indices [0, size/4-1].When i == size/4 - 1 on entry to an iteration and bit 14 of cmds[0] isset, bocmds[size/4-1] is written in bounds, i is then incremented tosize/4, and bocmds[size/4] writes four bytes past the end of theallocation.Userspace controls both the buffer contents and the size argument viathe ioctl, making this a userspace-triggerable heap out-of-bounds write.Fix by checking the incremented index against the buffer bound beforethe second write and returning -EINVAL if the buffer is too small tocontain the extended command.
A993: CVE-2026-53174 | B993: linux-image-7.0.0-29-generic | C993: hayzed | D993: Medium (Linux internal server) | E993: Not yet scored | F993: No | G993: =IF(E993="Not yet scored","Pending evaluation",IF(F993="Yes",IF(OR(E993="9.0-10.0 (Critical)",E993="7.0-8.9 (High)"),"P1 - Immediate","P2 - This week (elevated: in KEV)"),IF(OR(E993="9.0-10.0 (Critical)",E993="7.0-8.9 (High)"),"P2 - This week","P3 - Backlog"))) -> Pending evaluation | H993: In the Linux kernel, the following vulnerability has been resolved:ovl: keep err zero after successful ovl_cache_get()ovl_iterate_merged() stores PTR_ERR(cache) in err before checkingIS_ERR(cache). On success err holds the truncated cache pointer andcan be returned as a bogus non-zero error.The syzbot reproducer reaches this through overlay-on-overlay readdir: getdents64 iterate_dir(outer overlay file) ovl_iterate_merged() ovl_cache_get() ovl_dir_read_merged() ovl_dir_read() iterate_dir(inner overlay file) ovl_iterate_merged()Only compute PTR_ERR(cache) on the error path.
A994: CVE-2026-53175 | B994: linux-image-7.0.0-29-generic | C994: hayzed | D994: Medium (Linux internal server) | E994: Not yet scored | F994: No | G994: =IF(E994="Not yet scored","Pending evaluation",IF(F994="Yes",IF(OR(E994="9.0-10.0 (Critical)",E994="7.0-8.9 (High)"),"P1 - Immediate","P2 - This week (elevated: in KEV)"),IF(OR(E994="9.0-10.0 (Critical)",E994="7.0-8.9 (High)"),"P2 - This week","P3 - Backlog"))) -> Pending evaluation | H994: In the Linux kernel, the following vulnerability has been resolved:inet: frags: fix use-after-free caused by the fqdir_pre_exit() flushOn netns teardown, fqdir_pre_exit() walks the fqdir rhashtable andflushes every fragment queue that is not yet complete usinginet_frag_queue_flush(). That helper frees all the skbs queued on thefragment queue but does not set INET_FRAG_COMPLETE, and leavesq->fragments_tail and q->last_run_head pointing at the freed skbs.The queue itself stays in the rhashtable.fqdir_pre_exit() first lowers high_thresh to 0 to stop new queue lookups,but it cannot stop a fragment that already obtained the queue throughinet_frag_find() earlier and stalled just before taking the queue lock.Once that fragment resumes after the flush and takes the queue lock,it passes the INET_FRAG_COMPLETE check and then dereferences the freedfragments_tail. inet_frag_queue_insert() reads FRAG_CB() and ->len ofthat pointer and, on the append path, writes ->next_frag, causing aslab use-after-free. IPv6, nf_conntrack_reasm6 and 6lowpan reassemblyshare the same flush path and are affected as well.Reset rb_fragments, fragments_tail and last_run_head ininet_frag_queue_flush() so a flushed queue no longer points at thefreed skbs. A fragment that resumes after the flush and takes thequeue lock then finds an empty queue and starts a new run instead ofdereferencing the freed fragments_tail. ip_frag_reinit() alreadyperformed this reset after its own flush, so drop the now duplicatecode there.
A995: CVE-2026-53176 | B995: linux-image-7.0.0-29-generic | C995: hayzed | D995: Medium (Linux internal server) | E995: Not yet scored | F995: No | G995: =IF(E995="Not yet scored","Pending evaluation",IF(F995="Yes",IF(OR(E995="9.0-10.0 (Critical)",E995="7.0-8.9 (High)"),"P1 - Immediate","P2 - This week (elevated: in KEV)"),IF(OR(E995="9.0-10.0 (Critical)",E995="7.0-8.9 (High)"),"P2 - This week","P3 - Backlog"))) -> Pending evaluation | H995: In the Linux kernel, the following vulnerability has been resolved:IB/isert: Reject login PDUs shorter than ISER_HEADERS_LENIn drivers/infiniband/ulp/isert/ib_isert.c, isert_login_recv_done()computes the login request payload length as wc->byte_len minusISER_HEADERS_LEN with no lower bound, and login_req_len is a signed int.A remote iSER initiator can post a login Send work request carryingfewer than ISER_HEADERS_LEN (76) bytes, so the subtraction underflowsand login_req_len becomes negative.isert_rx_login_req() then reads that negative length back into a signedint, takes size = min(rx_buflen, MAX_KEY_VALUE_PAIRS), and because themin() is signed it keeps the negative value; the value is then passed asthe memcpy() length and sign-extended to a multi-gigabyte size_t. Thecopy into the 8192-byte login->req_buf runs far out of bounds andfaults, crashing the target node. The login phase precedes iSCSIauthentication, so no credentials are required to reach this path.Reject any login PDU shorter than ISER_HEADERS_LEN before thesubtraction, mirroring the existing early return on a failed workcompletion, so login_req_len can never go negative. The upper bound wasalready safe: a posted login buffer cannot deliver more thanISER_RX_PAYLOAD_SIZE, so the difference stays at or belowMAX_KEY_VALUE_PAIRS and the existing min() clamps it; only the missinglower bound needs to be added.
A996: CVE-2026-53177 | B996: linux-image-7.0.0-29-generic | C996: hayzed | D996: Medium (Linux internal server) | E996: Not yet scored | F996: No | G996: =IF(E996="Not yet scored","Pending evaluation",IF(F996="Yes",IF(OR(E996="9.0-10.0 (Critical)",E996="7.0-8.9 (High)"),"P1 - Immediate","P2 - This week (elevated: in KEV)"),IF(OR(E996="9.0-10.0 (Critical)",E996="7.0-8.9 (High)"),"P2 - This week","P3 - Backlog"))) -> Pending evaluation
A997: CVE-2026-53178 | B997: linux-image-7.0.0-29-generic | C997: hayzed | D997: Medium (Linux internal server) | E997: Not yet scored | F997: No | G997: =IF(E997="Not yet scored","Pending evaluation",IF(F997="Yes",IF(OR(E997="9.0-10.0 (Critical)",E997="7.0-8.9 (High)"),"P1 - Immediate","P2 - This week (elevated: in KEV)"),IF(OR(E997="9.0-10.0 (Critical)",E997="7.0-8.9 (High)"),"P2 - This week","P3 - Backlog"))) -> Pending evaluation | H997: In the Linux kernel, the following vulnerability has been resolved:staging: rtl8723bs: rtw_mlme: add bounds checks before ie_lengthsubtractionAdd guards to ensure ie_length is large enough before subtractingfixed IE offsets to prevent unsigned integer underflow.
A998: CVE-2026-53179 | B998: linux-image-7.0.0-29-generic | C998: hayzed | D998: Medium (Linux internal server) | E998: Not yet scored | F998: No | G998: =IF(E998="Not yet scored","Pending evaluation",IF(F998="Yes",IF(OR(E998="9.0-10.0 (Critical)",E998="7.0-8.9 (High)"),"P1 - Immediate","P2 - This week (elevated: in KEV)"),IF(OR(E998="9.0-10.0 (Critical)",E998="7.0-8.9 (High)"),"P2 - This week","P3 - Backlog"))) -> Pending evaluation | H998: In the Linux kernel, the following vulnerability has been resolved:staging: rtl8723bs: fix buffer over-read in rtw_update_protectionrtw_update_protection() is called with a pointer offset into theies buffer but the full ie_length is passed, causing a potentialbuffer over-read.
A999: CVE-2026-53180 | B999: linux-image-7.0.0-29-generic | C999: hayzed | D999: Medium (Linux internal server) | E999: Not yet scored | F999: No | G999: =IF(E999="Not yet scored","Pending evaluation",IF(F999="Yes",IF(OR(E999="9.0-10.0 (Critical)",E999="7.0-8.9 (High)"),"P1 - Immediate","P2 - This week (elevated: in KEV)"),IF(OR(E999="9.0-10.0 (Critical)",E999="7.0-8.9 (High)"),"P2 - This week","P3 - Backlog"))) -> Pending evaluation | H999: In the Linux kernel, the following vulnerability has been resolved:timers/migration: Fix livelock in tmigr_handle_remote_up()tmigr_handle_remote_cpu() skips timer_expire_remote() when cpu ==smp_processor_id(), assuming the local softirq path already handled thisCPU's timers.This assumption is wrong because jiffies can advance after the handling ofthe CPU's global timers in run_timer_base(BASE_GLOBAL) and beforetmigr_handle_remote() evaluates the expiry times.As a consequence a timer which expires after the CPU local timer wheeladvanced and becomes expired in the remote handling is ignored and thecallback is never invoked and removed from the timer wheel.What's worse is that fetch_next_timer_interrupt_remote() keeps reporting itas expired, and the event is re-queued with expires == now on eachiteration. The goto-again loop spins indefinitely.Fix this by calling timer_expire_remote() unconditionally. That's minimaloverhead for the common case as __run_timer_base() returns immediately ifthere is nothing to expire in the local wheel.[ tglx: Amend change log and add a comment ]
A1000: CVE-2026-53181 | B1000: linux-image-7.0.0-29-generic | C1000: hayzed | D1000: Medium (Linux internal server) | E1000: Not yet scored | F1000: No | G1000: =IF(E1000="Not yet scored","Pending evaluation",IF(F1000="Yes",IF(OR(E1000="9.0-10.0 (Critical)",E1000="7.0-8.9 (High)"),"P1 - Immediate","P2 - This week (elevated: in KEV)"),IF(OR(E1000="9.0-10.0 (Critical)",E1000="7.0-8.9 (High)"),"P2 - This week","P3 - Backlog"))) -> Pending evaluation | H1000: In the Linux kernel, the following vulnerability has been resolved:vsock/vmci: fix sk_ack_backlog leak on failed handshakeWhen vmci_transport_recv_connecting_server() returns an error,vmci_transport_recv_listen() calls vsock_remove_pending() but nevercalls sk_acceptq_removed(). This leaves sk_ack_backlog incrementedpermanently.Repeated handshake failures (malformed packets, queue pair allocfailure, event subscribe failure) cause sk_ack_backlog to climbtoward sk_max_ack_backlog. Once it reaches the limit the listenerpermanently refuses all new connections with -ECONNREFUSED, asilent denial of service requiring a process restart to recover.The two existing sk_acceptq_removed() calls in af_vsock.c do notcover this path: line 764 checks vsock_is_pending() which returnsfalse after vsock_remove_pending(), and line 1889 is only reachedon successful accept().Fix by balancing sk_acceptq_added() with sk_acceptq_removed() onthe error path.
A1001: CVE-2026-53182 | B1001: linux-image-7.0.0-29-generic | C1001: hayzed | D1001: Medium (Linux internal server) | E1001: Not yet scored | F1001: No | G1001: =IF(E1001="Not yet scored","Pending evaluation",IF(F1001="Yes",IF(OR(E1001="9.0-10.0 (Critical)",E1001="7.0-8.9 (High)"),"P1 - Immediate","P2 - This week (elevated: in KEV)"),IF(OR(E1001="9.0-10.0 (Critical)",E1001="7.0-8.9 (High)"),"P2 - This week","P3 - Backlog"))) -> Pending evaluation
A1002: CVE-2026-53183 | B1002: linux-image-7.0.0-29-generic | C1002: hayzed | D1002: Medium (Linux internal server) | E1002: Not yet scored | F1002: No | G1002: =IF(E1002="Not yet scored","Pending evaluation",IF(F1002="Yes",IF(OR(E1002="9.0-10.0 (Critical)",E1002="7.0-8.9 (High)"),"P1 - Immediate","P2 - This week (elevated: in KEV)"),IF(OR(E1002="9.0-10.0 (Critical)",E1002="7.0-8.9 (High)"),"P2 - This week","P3 - Backlog"))) -> Pending evaluation
A1003: CVE-2026-53184 | B1003: linux-image-7.0.0-29-generic | C1003: hayzed | D1003: Medium (Linux internal server) | E1003: Not yet scored | F1003: No | G1003: =IF(E1003="Not yet scored","Pending evaluation",IF(F1003="Yes",IF(OR(E1003="9.0-10.0 (Critical)",E1003="7.0-8.9 (High)"),"P1 - Immediate","P2 - This week (elevated: in KEV)"),IF(OR(E1003="9.0-10.0 (Critical)",E1003="7.0-8.9 (High)"),"P2 - This week","P3 - Backlog"))) -> Pending evaluation
A1004: CVE-2026-53185 | B1004: linux-image-7.0.0-29-generic | C1004: hayzed | D1004: Medium (Linux internal server) | E1004: Not yet scored | F1004: No | G1004: =IF(E1004="Not yet scored","Pending evaluation",IF(F1004="Yes",IF(OR(E1004="9.0-10.0 (Critical)",E1004="7.0-8.9 (High)"),"P1 - Immediate","P2 - This week (elevated: in KEV)"),IF(OR(E1004="9.0-10.0 (Critical)",E1004="7.0-8.9 (High)"),"P2 - This week","P3 - Backlog"))) -> Pending evaluation
A1005: CVE-2026-53186 | B1005: linux-image-7.0.0-29-generic | C1005: hayzed | D1005: Medium (Linux internal server) | E1005: Not yet scored | F1005: No | G1005: =IF(E1005="Not yet scored","Pending evaluation",IF(F1005="Yes",IF(OR(E1005="9.0-10.0 (Critical)",E1005="7.0-8.9 (High)"),"P1 - Immediate","P2 - This week (elevated: in KEV)"),IF(OR(E1005="9.0-10.0 (Critical)",E1005="7.0-8.9 (High)"),"P2 - This week","P3 - Backlog"))) -> Pending evaluation
A1006: CVE-2026-53187 | B1006: linux-image-7.0.0-29-generic | C1006: hayzed | D1006: Medium (Linux internal server) | E1006: Not yet scored | F1006: No | G1006: =IF(E1006="Not yet scored","Pending evaluation",IF(F1006="Yes",IF(OR(E1006="9.0-10.0 (Critical)",E1006="7.0-8.9 (High)"),"P1 - Immediate","P2 - This week (elevated: in KEV)"),IF(OR(E1006="9.0-10.0 (Critical)",E1006="7.0-8.9 (High)"),"P2 - This week","P3 - Backlog"))) -> Pending evaluation
A1007: CVE-2026-53188 | B1007: linux-image-7.0.0-29-generic | C1007: hayzed | D1007: Medium (Linux internal server) | E1007: Not yet scored | F1007: No | G1007: =IF(E1007="Not yet scored","Pending evaluation",IF(F1007="Yes",IF(OR(E1007="9.0-10.0 (Critical)",E1007="7.0-8.9 (High)"),"P1 - Immediate","P2 - This week (elevated: in KEV)"),IF(OR(E1007="9.0-10.0 (Critical)",E1007="7.0-8.9 (High)"),"P2 - This week","P3 - Backlog"))) -> Pending evaluation
A1008: CVE-2026-53189 | B1008: linux-image-7.0.0-29-generic | C1008: hayzed | D1008: Medium (Linux internal server) | E1008: Not yet scored | F1008: No | G1008: =IF(E1008="Not yet scored","Pending evaluation",IF(F1008="Yes",IF(OR(E1008="9.0-10.0 (Critical)",E1008="7.0-8.9 (High)"),"P1 - Immediate","P2 - This week (elevated: in KEV)"),IF(OR(E1008="9.0-10.0 (Critical)",E1008="7.0-8.9 (High)"),"P2 - This week","P3 - Backlog"))) -> Pending evaluation
A1009: CVE-2026-53190 | B1009: linux-image-7.0.0-29-generic | C1009: hayzed | D1009: Medium (Linux internal server) | E1009: Not yet scored | F1009: No | G1009: =IF(E1009="Not yet scored","Pending evaluation",IF(F1009="Yes",IF(OR(E1009="9.0-10.0 (Critical)",E1009="7.0-8.9 (High)"),"P1 - Immediate","P2 - This week (elevated: in KEV)"),IF(OR(E1009="9.0-10.0 (Critical)",E1009="7.0-8.9 (High)"),"P2 - This week","P3 - Backlog"))) -> Pending evaluation
A1010: CVE-2026-53191 | B1010: linux-image-7.0.0-29-generic | C1010: hayzed | D1010: Medium (Linux internal server) | E1010: Not yet scored | F1010: No | G1010: =IF(E1010="Not yet scored","Pending evaluation",IF(F1010="Yes",IF(OR(E1010="9.0-10.0 (Critical)",E1010="7.0-8.9 (High)"),"P1 - Immediate","P2 - This week (elevated: in KEV)"),IF(OR(E1010="9.0-10.0 (Critical)",E1010="7.0-8.9 (High)"),"P2 - This week","P3 - Backlog"))) -> Pending evaluation
A1011: CVE-2026-53192 | B1011: linux-image-7.0.0-29-generic | C1011: hayzed | D1011: Medium (Linux internal server) | E1011: Not yet scored | F1011: No | G1011: =IF(E1011="Not yet scored","Pending evaluation",IF(F1011="Yes",IF(OR(E1011="9.0-10.0 (Critical)",E1011="7.0-8.9 (High)"),"P1 - Immediate","P2 - This week (elevated: in KEV)"),IF(OR(E1011="9.0-10.0 (Critical)",E1011="7.0-8.9 (High)"),"P2 - This week","P3 - Backlog"))) -> Pending evaluation
A1012: CVE-2026-53193 | B1012: linux-image-7.0.0-29-generic | C1012: hayzed | D1012: Medium (Linux internal server) | E1012: Not yet scored | F1012: No | G1012: =IF(E1012="Not yet scored","Pending evaluation",IF(F1012="Yes",IF(OR(E1012="9.0-10.0 (Critical)",E1012="7.0-8.9 (High)"),"P1 - Immediate","P2 - This week (elevated: in KEV)"),IF(OR(E1012="9.0-10.0 (Critical)",E1012="7.0-8.9 (High)"),"P2 - This week","P3 - Backlog"))) -> Pending evaluation
... A1088: CVE-2026-53275 | B1088: linux-image-7.0.0-29-generic | C1088: hayzed | D1088: Medium (Linux internal server) | E1088: Not yet scored | F1088: No | G1088: =IF(E1088="Not yet scored","Pending evaluation",IF(F1088="Yes",IF(OR(E1088="9.0-10.0 (Critical)",E1088="7.0-8.9 (High)"),"P1 - Immediate","P2 - This week (elevated: in KEV)"),IF(OR(E1088="9.0-10.0 (Critical)",E1088="7.0-8.9 (High)"),"P2 - This week","P3 - Backlog"))) -> Pending evaluation

Sheet Summary
A1: Prioritization Summary (all findings, live count)
A2: Total findings scored | B2: =COUNTA('All Findings'!A2:A1088) -> 1087
A3: P1 - Immediate | B3: =COUNTIF('All Findings'!G2:G1088,"P1 - Immediate") -> 1
A4: P2 - This week (Critical/High) | B4: =COUNTIF('All Findings'!G2:G1088,"P2 - This week") -> 461
A5: P2 - This week (elevated: in KEV) | B5: =COUNTIF('All Findings'!G2:G1088,"P2 - This week (elevated: in KEV)") -> 1
A6: P3 - Backlog | B6: =COUNTIF('All Findings'!G2:G1088,"P3 - Backlog") -> 335
A7: Pending evaluation (not yet scored by feed) | B7: =COUNTIF('All Findings'!G2:G1088,"Pending evaluation") -> 289
A9: P1 Justification
A10: CVE-2026-33824 | B10: Prioritized as P1 because it carries a Critical CVSS score, is confirmed in the CISA KEV catalog as actively exploited in the wild, and affects the domain-facing Windows endpoint, the highest criticality asset in this environment.
A12: Note on the elevated P2 finding
A13: CVE-2026-32202 (Medium severity, Windows Shell spoofing) is also confirmed in CISA KEV, meaning it is being actively exploited despite its lower CVSS band. It is not treated as P1 alongside CVE-2026-33824 because its severity and impact (spoofing) are materially lower than the Critical, remote-code-execution P1 finding, but it is pulled out of the standard backlog into this week's work given confirmed active exploitation.
A15: Known false-positive pattern (within the P3 backlog)
A16: 34 findings in the P3 backlog are pre-2021 CVEs (e.g. CVE-2017-13716, flagged 8 times) matched against currently supported Ubuntu 26.04 packages. This is a known false-positive pattern in NVD-based scanning: Ubuntu backports security fixes into its package builds without changing the upstream version string the scanner checks against. Flagged as likely false positives pending manual changelog verification, left in the P3 backlog rather than removed outright.
